random_quote_generator/__init__.py
random_quote_generator/get_quote.py
random_quote_generator/quotes.py
random_quote_generator_728678-0.1.0.dist-info/LICENSE
random_quote_generator_728678-0.1.0.dist-info/WHEEL
random_quote_generator_728678-0.1.0.dist-info/METADATA
random_quote_generator_728678-0.1.0.dist-info/RECORD
