Metadata-Version: 2.1
Name: random-quote-generator-728678
Version: 0.1.0
Summary: Random Quote Generator
Author: martin
Author-email: hewingmartin@gmail.com
Requires-Python: >=3.9,<4.0
Classifier: Programming Language :: Python :: 3
Classifier: Programming Language :: Python :: 3.10
Classifier: Programming Language :: Python :: 3.9
